smsc/__init__.py
smsc/__version__.py
smsc/api.py
smsc/exceptions.py
smsc/messages.py
smsc/responses.py
smsc-0.1.1.dist-info/DESCRIPTION.rst
smsc-0.1.1.dist-info/METADATA
smsc-0.1.1.dist-info/RECORD
smsc-0.1.1.dist-info/WHEEL
smsc-0.1.1.dist-info/metadata.json
smsc-0.1.1.dist-info/top_level.txt
