Metadata-Version: 2.0
Name: smsc
Version: 0.1.1
Summary: SMSC.ru HTTP API Library.
Home-page: https://github.com/Otetz/smsc/
Author: Alexey Shevchenko
Author-email: otetz@me.com
License: MIT
Keywords: smsc sms
Platform: UNKNOWN
Classifier: Intended Audience :: Developers
Classifier: Intended Audience :: Information Technology
Classifier: Topic :: Software Development :: Libraries
Classifier: Natural Language :: English
Classifier: License :: OSI Approved :: MIT License
Classifier: Programming Language :: Python
Classifier: Programming Language :: Python :: 3
Classifier: Programming Language :: Python :: 3.3
Classifier: Programming Language :: Python :: 3.4
Classifier: Programming Language :: Python :: 3.5
Classifier: Programming Language :: Python :: 3.6
Requires-Dist: arrow
Requires-Dist: furl
Requires-Dist: requests
Requires-Dist: typing
